tests/__init__.py
tests/collection.py
tests/discovery.py
tests/evasion.py
tests/execution.py
tests/exfiltration.py
tests/persistense.py
evil_package-0.0.3.dist-info/LICENSE
evil_package-0.0.3.dist-info/METADATA
evil_package-0.0.3.dist-info/WHEEL
evil_package-0.0.3.dist-info/top_level.txt
evil_package-0.0.3.dist-info/RECORD
